crypto_msg_parser/__init__.py
crypto_msg_parser/_lowlevel.py
crypto_msg_parser/_lowlevel__ffi.py
crypto_msg_parser/_lowlevel__lib.so
crypto_msg_parser-2.8.16.dist-info/LICENSE
crypto_msg_parser-2.8.16.dist-info/METADATA
crypto_msg_parser-2.8.16.dist-info/WHEEL
crypto_msg_parser-2.8.16.dist-info/top_level.txt
crypto_msg_parser-2.8.16.dist-info/RECORD
crypto_msg_parser.libs/libgssapi_krb5-497db0c6.so.2.2
crypto_msg_parser.libs/libkrb5-fc820a1d.so.3.3
crypto_msg_parser.libs/libcrypto-19957f5b.so.1.0.2k
crypto_msg_parser.libs/libk5crypto-b1f99d5c.so.3.1
crypto_msg_parser.libs/libcom_err-2abe824b.so.2.1
crypto_msg_parser.libs/libssl-2a9eae6f.so.1.0.2k
crypto_msg_parser.libs/libkrb5support-a4e68a84.so.0.1
crypto_msg_parser.libs/libkeyutils-dfe70bd6.so.1.5
crypto_msg_parser.libs/libpcre-9513aab5.so.1.2.0
crypto_msg_parser.libs/libselinux-0922c95c.so.1
