Metadata-Version: 2.1
Name: crypto-msg-parser
Version: 2.8.16
Summary: Parse websocket messages from cryptocurreny exchanges
Home-page: https://github.com/soulmachine/crypto-msg-parser-py
Author: soulmachine
License: Apache License 2.0
Keywords: blockchain,cryptocurrency,trading
Platform: UNKNOWN
Classifier: Programming Language :: Python :: 3.6
Classifier: License :: OSI Approved :: Apache Software License
Classifier: Topic :: Software Development :: Libraries :: Python Modules
Requires-Python: >=3.6
License-File: LICENSE
Requires-Dist: cffi
Requires-Dist: result
